fifslack-bitbucket-pr-reminder.py
fifslack_bitbucket_pr_reminder.py
fifslack_bitbucket_pr_reminder-0.0.7.dist-info/DESCRIPTION.rst
fifslack_bitbucket_pr_reminder-0.0.7.dist-info/METADATA
fifslack_bitbucket_pr_reminder-0.0.7.dist-info/RECORD
fifslack_bitbucket_pr_reminder-0.0.7.dist-info/WHEEL
fifslack_bitbucket_pr_reminder-0.0.7.dist-info/entry_points.txt
fifslack_bitbucket_pr_reminder-0.0.7.dist-info/metadata.json
fifslack_bitbucket_pr_reminder-0.0.7.dist-info/top_level.txt
