Metadata-Version: 2.0
Name: fifslack-bitbucket-pr-reminder
Version: 0.0.7
Summary: Posts a Slack reminder with a list of open pull requests for an organization
Home-page: http://github.com/ordenador/fifslack-bitbucket-pr-reminder
Author: Mario Faundez
Author-email: mariofaundez@hotmail.com
License: MIT
Platform: UNKNOWN
Requires-Dist: fifbucket (==0.7)
Requires-Dist: slackclient (==1.1.3)
